fastled_wasm_compiler/__init__.py
fastled_wasm_compiler/args.py
fastled_wasm_compiler/build_flags.toml
fastled_wasm_compiler/build_lib_lazy.py
fastled_wasm_compiler/cli.py
fastled_wasm_compiler/cli_build_lib_lazy.py
fastled_wasm_compiler/cli_native.py
fastled_wasm_compiler/cli_prewarm.py
fastled_wasm_compiler/cli_printenv.py
fastled_wasm_compiler/cli_symbol_resolution.py
fastled_wasm_compiler/cli_update_from_master.py
fastled_wasm_compiler/compilation_flags.py
fastled_wasm_compiler/compile.py
fastled_wasm_compiler/compile_all_libs.py
fastled_wasm_compiler/compile_lib.py
fastled_wasm_compiler/compile_sketch.py
fastled_wasm_compiler/compile_sketch_native.py
fastled_wasm_compiler/compiler.py
fastled_wasm_compiler/copy_files_and_output_manifest.py
fastled_wasm_compiler/dump_headers.py
fastled_wasm_compiler/dwarf_path_to_file_path.py
fastled_wasm_compiler/emsdk_manager.py
fastled_wasm_compiler/env_validation.py
fastled_wasm_compiler/fastled_downloader.py
fastled_wasm_compiler/hashfile.py
fastled_wasm_compiler/insert_header.py
fastled_wasm_compiler/line_ending_pool.py
fastled_wasm_compiler/list_headers.py
fastled_wasm_compiler/open_process.py
fastled_wasm_compiler/paths.py
fastled_wasm_compiler/print_banner.py
fastled_wasm_compiler/process_ino_files.py
fastled_wasm_compiler/run_compile.py
fastled_wasm_compiler/run_compile_easy.py
fastled_wasm_compiler/sketch_hasher.py
fastled_wasm_compiler/streaming_timestamper.py
fastled_wasm_compiler/sync.py
fastled_wasm_compiler/timestamp_utils.py
fastled_wasm_compiler/transform_to_cpp.py
fastled_wasm_compiler/types.py
fastled_wasm_compiler/assets/example.txt
fastled_wasm_compiler-1.1.7.dist-info/licenses/LICENSE
fastled_wasm_compiler-1.1.7.dist-info/METADATA
fastled_wasm_compiler-1.1.7.dist-info/WHEEL
fastled_wasm_compiler-1.1.7.dist-info/entry_points.txt
fastled_wasm_compiler-1.1.7.dist-info/top_level.txt
fastled_wasm_compiler-1.1.7.dist-info/RECORD
