Metadata-Version: 2.4
Name: fastled_wasm_compiler
Version: 1.1.7
Summary: Fastled Wasm Compiler
Home-page: https://github.com/zackees/fastled-wasm-compiler
Maintainer: Zachary Vorhies
License: BSD 3-Clause License
Keywords: template-python-cmd
Classifier: Programming Language :: Python :: 3
Requires-Python: >=3.10
License-File: LICENSE
Requires-Dist: black>=25.1.0
Requires-Dist: fasteners==0.19
Requires-Dist: httpx>=0.28.1
Requires-Dist: tomli>=2.2.1
Provides-Extra: test
Requires-Dist: pytest; extra == "test"
Requires-Dist: pytest-xdist; extra == "test"
Requires-Dist: ruff; extra == "test"
Requires-Dist: pyright; extra == "test"
Requires-Dist: isort; extra == "test"
Dynamic: home-page
Dynamic: license-file
Dynamic: maintainer
